[
    {
        "name": "Preparebehavior",
        "email": "arseni68@example.net",
        "url": "https://www.zao.org/",
        "datecreate": "2019-12-10",
        "datechange": "2019-12-30"
    },
    {
        "name": "Picturedrive",
        "email": "efim1985@example.com",
        "url": "https://ao.edu/",
        "datecreate": "2020-08-21",
        "datechange": "2023-01-04"
    },
    {
        "name": "Whenrate",
        "email": "avksenti1992@example.com",
        "url": "http://zao.biz/",
        "datecreate": "2023-08-17",
        "datechange": "2024-02-12"
    },
    {
        "name": "Iphysical",
        "email": "wzimina@example.com",
        "url": "https://rao.edu/",
        "datecreate": "2023-05-18",
        "datechange": "2023-08-07"
    },
    {
        "name": "Marriageblood",
        "email": "vseslav31@example.net",
        "url": "http://www.npo.edu/",
        "datecreate": "2024-07-24",
        "datechange": "2024-08-06"
    },
    {
        "name": "Himfollow",
        "email": "muravevakim@example.org",
        "url": "http://rao.info/",
        "datecreate": "2021-04-23",
        "datechange": "2024-09-12"
    },
    {
        "name": "Continuemuch",
        "email": "fadeaksenov@example.net",
        "url": "https://sovkombank.ru/",
        "datecreate": "2023-08-08",
        "datechange": "2024-05-25"
    },
    {
        "name": "Myselfunit",
        "email": "ckomissarov@example.com",
        "url": "http://sberbank.info/",
        "datecreate": "2021-12-06",
        "datechange": "2022-06-16"
    },
    {
        "name": "Securitysomeone",
        "email": "beljaevivan@example.net",
        "url": "https://gruppa.com/",
        "datecreate": "2020-02-07",
        "datechange": "2022-04-08"
    },
    {
        "name": "Technologylaw",
        "email": "haritonovserge@example.com",
        "url": "http://ooo.net/",
        "datecreate": "2020-07-06",
        "datechange": "2024-04-22"
    }
]